{"errors":[],"warnings":[],"namedChunkGroups":{"app":{"chunks":[5,2],"assets":["webpack-runtime-4a9437ec57f770c156d2.js","webpack-runtime-4a9437ec57f770c156d2.js.map","app-c8ddee5a02e8722318a2.js","app-c8ddee5a02e8722318a2.js.map"],"children":{},"childAssets":{}},"component---src-pages-404-js":{"chunks":[0,1,3],"assets":["0-6e2633137f1f4941f9e4.js","0-6e2633137f1f4941f9e4.js.map","1.29a26ff8463fb4fc9090.css","1-82f818a65771a6b23bd7.js","1-82f818a65771a6b23bd7.js.map","component---src-pages-404-js-ce6c59310fc148aa6c11.js","component---src-pages-404-js-ce6c59310fc148aa6c11.js.map"],"children":{},"childAssets":{}},"component---src-pages-index-js":{"chunks":[0,6,1,4],"assets":["0-6e2633137f1f4941f9e4.js","0-6e2633137f1f4941f9e4.js.map","6-47332009386587874f9d.js","6-47332009386587874f9d.js.map","1.29a26ff8463fb4fc9090.css","1-82f818a65771a6b23bd7.js","1-82f818a65771a6b23bd7.js.map","component---src-pages-index-js.80d8f9d4607a47b61386.css","component---src-pages-index-js-6daee6d5c4627119ad48.js","component---src-pages-index-js-6daee6d5c4627119ad48.js.map"],"children":{},"childAssets":{}}},"assetsByChunkName":{"app":["webpack-runtime-4a9437ec57f770c156d2.js","app-c8ddee5a02e8722318a2.js"],"component---src-pages-404-js":["0-6e2633137f1f4941f9e4.js","1.29a26ff8463fb4fc9090.css","1-82f818a65771a6b23bd7.js","component---src-pages-404-js-ce6c59310fc148aa6c11.js"],"component---src-pages-index-js":["0-6e2633137f1f4941f9e4.js","6-47332009386587874f9d.js","1.29a26ff8463fb4fc9090.css","1-82f818a65771a6b23bd7.js","component---src-pages-index-js.80d8f9d4607a47b61386.css","component---src-pages-index-js-6daee6d5c4627119ad48.js"]}}